LICENCE.txt
MANIFEST.in
README.rst
ez_setup.py
setup.py
chetan_moviepy.egg-info/PKG-INFO
chetan_moviepy.egg-info/SOURCES.txt
chetan_moviepy.egg-info/dependency_links.txt
chetan_moviepy.egg-info/requires.txt
chetan_moviepy.egg-info/top_level.txt
docs/FAQ.rst
docs/Makefile
docs/conf.py
docs/demo_preview.jpeg
docs/docker.rst
docs/gallery.rst
docs/index.rst
docs/install.rst
docs/logo.png
docs/make.bat
docs/makehtml.sh
docs/_static/logo.png
docs/_static/logo_small.jpeg
docs/_static/moviepy.css
docs/_themes/.gitignore
docs/advanced_tools/advanced_tools.py
docs/advanced_tools/advanced_tools.rst
docs/examples/compo_from_image.jpeg
docs/examples/compo_from_image.rst
docs/examples/dancing_knights.rst
docs/examples/example_with_sound.rst
docs/examples/examples.rst
docs/examples/headblur.rst
docs/examples/logo.rst
docs/examples/masked_credits.rst
docs/examples/moving_letters.rst
docs/examples/painting_effect.rst
docs/examples/quick_recipes.rst
docs/examples/several_characters.rst
docs/examples/star_worms.rst
docs/examples/the_end.rst
docs/examples/ukulele_concerto.rst
docs/getting_started/audioclips.rst
docs/getting_started/circle.gif
docs/getting_started/compositing.rst
docs/getting_started/effects.rst
docs/getting_started/efficient_moviepy.rst
docs/getting_started/explanations.jpeg
docs/getting_started/getting_started.rst
docs/getting_started/ipynb_example.jpeg
docs/getting_started/quick_presentation.rst
docs/getting_started/stacked.jpeg
docs/getting_started/videoWH.jpeg
docs/getting_started/videoclips.rst
docs/getting_started/working_with_matplotlib.rst
docs/ref/AudioClip.rst
docs/ref/Clip.rst
docs/ref/audiofx.rst
docs/ref/audiotools.rst
docs/ref/bideotools_gradient.jpeg
docs/ref/code_origanization.rst
docs/ref/decorators.rst
docs/ref/ffmpeg.rst
docs/ref/ref.rst
docs/ref/videofx.rst
docs/ref/videotools.rst
docs/ref/videotools_credits.jpeg
docs/ref/VideoClip/VideoClip.rst
docs/ref/audiofx/moviepy.audio.fx.all.audio_fadein.rst
docs/ref/audiofx/moviepy.audio.fx.all.audio_fadeout.rst
docs/ref/audiofx/moviepy.audio.fx.all.audio_loop.rst
docs/ref/audiofx/moviepy.audio.fx.all.audio_normalize.rst
docs/ref/audiofx/moviepy.audio.fx.all.volumex.rst
