Metadata-Version: 2.1
Name: chetan-moviepy
Version: 2.0.0.dev2
Summary: Video editing with Python
Home-page: https://zulko.github.io/moviepy/
Author: Zulko 2017
License: MIT License
Keywords: video editing audio compositing ffmpeg
Platform: UNKNOWN
Classifier: Development Status :: 5 - Production/Stable
Classifier: Intended Audience :: Developers
Classifier: Natural Language :: English
Classifier: License :: OSI Approved :: MIT License
Classifier: Programming Language :: Python
Classifier: Programming Language :: Python :: 3
Classifier: Programming Language :: Python :: 3.6
Classifier: Programming Language :: Python :: 3.7
Classifier: Programming Language :: Python :: 3.8
Classifier: Topic :: Multimedia
Classifier: Topic :: Multimedia :: Sound/Audio
Classifier: Topic :: Multimedia :: Sound/Audio :: Analysis
Classifier: Topic :: Multimedia :: Video
Classifier: Topic :: Multimedia :: Video :: Capture
Classifier: Topic :: Multimedia :: Video :: Conversion
Provides-Extra: optional
Provides-Extra: doc
Provides-Extra: test
License-File: LICENCE.txt
